src/Postrequest.py
src/QQScrape.py
src/__init__.py
src/find_db.py
src/main.py
src/run.py
src/webserver.py
ScrapeFinance-0.1.0.dist-info/METADATA
ScrapeFinance-0.1.0.dist-info/WHEEL
ScrapeFinance-0.1.0.dist-info/top_level.txt
ScrapeFinance-0.1.0.dist-info/RECORD
