Metadata-Version: 2.1
Name: ScrapeFinance
Version: 0.1.0
Summary: dry martini,shaken,not stirred
Home-page: https://github.com/raymond57p/ScrapeFinance
Author: frank
Author-email: henrywongb@hotmail.com
Requires-Dist: numpy
Requires-Dist: pandas
Requires-Dist: matplotlib
